{
	"info": {
		"_postman_id": "8b52f4eb-8a9d-4001-bb1d-84e5b61a382e",
		"name": "Laravel 12 REST API E-commerce",
		"description": "Postman Collection for CarbonEthics Backend Intern REST API business case.",
		"schema": "https://schema.getpostman.com/json/collection/v2.1.0/collection.json"
	},
	"item": [
		{
			"name": "Auth",
			"item": [
				{
					"name": "Login - Admin",
					"request": {
						"method": "POST",
						"header": [
							{
								"key": "Accept",
								"value": "application/json",
								"type": "text"
							}
						],
						"body": {
							"mode": "raw",
							"raw": "{\n    \"email\": \"admin@mail.com\",\n    \"password\": \"password123\"\n}",
							"options": {
								"raw": {
									"language": "json"
								}
							}
						},
						"url": {
							"raw": "{{base_url}}/api/login",
							"host": [
								"{{base_url}}"
							],
							"path": [
								"api",
								"login"
							]
						}
					},
					"response": []
				},
				{
					"name": "Login - User",
					"request": {
						"method": "POST",
						"header": [
							{
								"key": "Accept",
								"value": "application/json",
								"type": "text"
							}
						],
						"body": {
							"mode": "raw",
							"raw": "{\n    \"email\": \"budi@mail.com\",\n    \"password\": \"password123\"\n}",
							"options": {
								"raw": {
									"language": "json"
								}
							}
						},
						"url": {
							"raw": "{{base_url}}/api/login",
							"host": [
								"{{base_url}}"
							],
							"path": [
								"api",
								"login"
							]
						}
					},
					"response": []
				},
				{
					"name": "Logout",
					"request": {
						"auth": {
							"type": "bearer",
							"bearer": [
								{
									"key": "token",
									"value": "{{auth_token}}",
									"type": "string"
								}
							]
						},
						"method": "POST",
						"header": [
							{
								"key": "Accept",
								"value": "application/json",
								"type": "text"
							}
						],
						"url": {
							"raw": "{{base_url}}/api/logout",
							"host": [
								"{{base_url}}"
							],
							"path": [
								"api",
								"logout"
							]
						}
					},
					"response": []
				}
			]
		},
		{
			"name": "Products",
			"item": [
				{
					"name": "Get All Products",
					"request": {
						"method": "GET",
						"header": [
							{
								"key": "Accept",
								"value": "application/json",
								"type": "text"
							}
						],
						"url": {
							"raw": "{{base_url}}/api/products",
							"host": [
								"{{base_url}}"
							],
							"path": [
								"api",
								"products"
							]
						}
					},
					"response": []
				},
				{
					"name": "Get Single Product",
					"request": {
						"method": "GET",
						"header": [
							{
								"key": "Accept",
								"value": "application/json",
								"type": "text"
							}
						],
						"url": {
							"raw": "{{base_url}}/api/products/1",
							"host": [
								"{{base_url}}"
							],
							"path": [
								"api",
								"products",
								"1"
							]
						}
					},
					"response": []
				},
				{
					"name": "Create Product (Admin Only)",
					"request": {
						"auth": {
							"type": "bearer",
							"bearer": [
								{
									"key": "token",
									"value": "{{auth_token}}",
									"type": "string"
								}
							]
						},
						"method": "POST",
						"header": [
							{
								"key": "Accept",
								"value": "application/json",
								"type": "text"
							}
						],
						"body": {
							"mode": "raw",
							"raw": "{\n    \"name\": \"Mangrove Crackers\",\n    \"description\": \"Crispy, savory traditional crackers made from organic mangrove leaves by Tanjung Pakis coastal community. A delicious, eco-friendly snack.\",\n    \"price\": 1.49,\n    \"status\": \"active\"\n}",
							"options": {
								"raw": {
									"language": "json"
								}
							}
						},
						"url": {
							"raw": "{{base_url}}/api/products",
							"host": [
								"{{base_url}}"
							],
							"path": [
								"api",
								"products"
							]
						}
					},
					"response": []
				},
				{
					"name": "Update Product (Admin Only)",
					"request": {
						"auth": {
							"type": "bearer",
							"bearer": [
								{
									"key": "token",
									"value": "{{auth_token}}",
									"type": "string"
								}
							]
						},
						"method": "PUT",
						"header": [
							{
								"key": "Accept",
								"value": "application/json",
								"type": "text"
							}
						],
						"body": {
							"mode": "raw",
							"raw": "{\n    \"name\": \"Mangrove Soap Premium\",\n    \"description\": \"A premium, all-natural soap infused with organic mangrove extracts. Directly supports sustainable livelihoods for fishermen and protects Dompak Island's biodiversity.\",\n    \"price\": 3.48,\n    \"status\": \"active\"\n}",
							"options": {
								"raw": {
									"language": "json"
								}
							}
						},
						"url": {
							"raw": "{{base_url}}/api/products/1",
							"host": [
								"{{base_url}}"
							],
							"path": [
								"api",
								"products",
								"1"
							]
						}
					},
					"response": []
				},
				{
					"name": "Delete Product (Admin Only)",
					"request": {
						"auth": {
							"type": "bearer",
							"bearer": [
								{
									"key": "token",
									"value": "{{auth_token}}",
									"type": "string"
								}
							]
						},
						"method": "DELETE",
						"header": [
							{
								"key": "Accept",
								"value": "application/json",
								"type": "text"
							}
						],
						"url": {
							"raw": "{{base_url}}/api/products/1",
							"host": [
								"{{base_url}}"
							],
							"path": [
								"api",
								"products",
								"1"
							]
						}
					},
					"response": []
				}
			]
		},
		{
			"name": "Orders",
			"item": [
				{
					"name": "Create Order (Public)",
					"request": {
						"method": "POST",
						"header": [
							{
								"key": "Accept",
								"value": "application/json",
								"type": "text"
							}
						],
						"body": {
							"mode": "raw",
							"raw": "{\n    \"customer_name\": \"Budi\",\n    \"customer_email\": \"budi@mail.com\",\n    \"items\": [\n        { \"product_id\": 1, \"qty\": 2 }\n    ]\n}",
							"options": {
								"raw": {
									"language": "json"
								}
							}
						},
						"url": {
							"raw": "{{base_url}}/api/orders",
							"host": [
								"{{base_url}}"
							],
							"path": [
								"api",
								"orders"
							]
						}
					},
					"response": []
				},
				{
					"name": "Get All Orders (Admin Only)",
					"request": {
						"auth": {
							"type": "bearer",
							"bearer": [
								{
									"key": "token",
									"value": "{{auth_token}}",
									"type": "string"
								}
							]
						},
						"method": "GET",
						"header": [
							{
								"key": "Accept",
								"value": "application/json",
								"type": "text"
							}
						],
						"url": {
							"raw": "{{base_url}}/api/orders",
							"host": [
								"{{base_url}}"
							],
							"path": [
								"api",
								"orders"
							]
						}
					},
					"response": []
				},
				{
					"name": "Get Single Order (Admin Only)",
					"request": {
						"auth": {
							"type": "bearer",
							"bearer": [
								{
									"key": "token",
									"value": "{{auth_token}}",
									"type": "string"
								}
							]
						},
						"method": "GET",
						"header": [
							{
								"key": "Accept",
								"value": "application/json",
								"type": "text"
							}
						],
						"url": {
							"raw": "{{base_url}}/api/orders/1",
							"host": [
								"{{base_url}}"
							],
							"path": [
								"api",
								"orders",
								"1"
							]
						}
					},
					"response": []
				}
			]
		}
	],
	"variable": [
		{
			"key": "base_url",
			"value": "http://127.0.0.1:8000",
			"type": "string"
		},
		{
			"key": "auth_token",
			"value": "PASTE_YOUR_BEARER_TOKEN_HERE",
			"type": "string"
		}
	]
}
